MANIFEST.in
README.rst
setup.py
django_readonly.egg-info/PKG-INFO
django_readonly.egg-info/SOURCES.txt
django_readonly.egg-info/dependency_links.txt
django_readonly.egg-info/not-zip-safe
django_readonly.egg-info/requires.txt
django_readonly.egg-info/top_level.txt
readonly/__init__.py
readonly/middleware.py