Metadata-Version: 1.1
Name: django-readonly
Version: 0.1.2
Summary: Put website in read-only mode for maintenance.
Home-page: https://bitbucket.org/zalew/django-readonly
Author: Jakub Zalewski
Author-email: zalew7@gmail.com
License: BSD License
Keywords: django readonly
Platform: UNKNOWN
Classifier: Development Status :: 3 - Alpha
Classifier: Environment :: Web Environment
Classifier: Intended Audience :: Developers
Classifier: License :: OSI Approved :: BSD License
Classifier: Operating System :: OS Independent
Classifier: Programming Language :: Python
Classifier: Programming Language :: Python :: 2
Classifier: Framework :: Django
